jupyter_session_tracer/__init__.py
jupyter_session_tracer/_version.py
jupyter_session_tracer/labextension/package.json
jupyter_session_tracer/labextension/schemas/jupyter-session-tracer/package.json.orig
jupyter_session_tracer/labextension/static/181.cd6c8c5ccfa952559d42.js
jupyter_session_tracer/labextension/static/920.e208e47ad9178f541e4c.js
jupyter_session_tracer/labextension/static/remoteEntry.4416f97896959c2bfaa9.js
jupyter_session_tracer/labextension/static/style.js
jupyter_session_tracer/labextension/static/third-party-licenses.json
jupyter_session_tracer-0.1.2.data/data/share/jupyter/labextensions/jupyter-session-tracer/package.json
jupyter_session_tracer-0.1.2.data/data/share/jupyter/labextensions/jupyter-session-tracer/schemas/jupyter-session-tracer/package.json.orig
jupyter_session_tracer-0.1.2.data/data/share/jupyter/labextensions/jupyter-session-tracer/static/181.cd6c8c5ccfa952559d42.js
jupyter_session_tracer-0.1.2.data/data/share/jupyter/labextensions/jupyter-session-tracer/static/920.e208e47ad9178f541e4c.js
jupyter_session_tracer-0.1.2.data/data/share/jupyter/labextensions/jupyter-session-tracer/static/remoteEntry.4416f97896959c2bfaa9.js
jupyter_session_tracer-0.1.2.data/data/share/jupyter/labextensions/jupyter-session-tracer/static/style.js
jupyter_session_tracer-0.1.2.data/data/share/jupyter/labextensions/jupyter-session-tracer/static/third-party-licenses.json
jupyter_session_tracer-0.1.2.data/data/share/jupyter/labextensions/jupyter-session-tracer/install.json
jupyter_session_tracer-0.1.2.dist-info/METADATA
jupyter_session_tracer-0.1.2.dist-info/WHEEL
jupyter_session_tracer-0.1.2.dist-info/licenses/LICENSE
jupyter_session_tracer-0.1.2.dist-info/RECORD
