Metadata-Version: 2.4
Name: jupyter_session_tracer
Version: 0.1.2
Dynamic: Keywords
Summary: A JupyterLab extension that displays session information in a beautiful popup with automatic clipboard copying
Project-URL: Homepage, https://github.com/wenmin-wu/jupyter-session-tracer
Project-URL: Bug Tracker, https://github.com/wenmin-wu/jupyter-session-tracer/issues
Project-URL: Repository, https://github.com/wenmin-wu/jupyter-session-tracer.git
Author-email: wenmin-wu <wuwenmin1991@gmail.com>
License: BSD-3-Clause License
License-File: LICENSE
Classifier: Framework :: Jupyter
Classifier: Framework :: Jupyter :: JupyterLab
Classifier: Framework :: Jupyter :: JupyterLab :: 4
Classifier: Framework :: Jupyter :: JupyterLab :: Extensions
Classifier: Framework :: Jupyter :: JupyterLab :: Extensions :: Prebuilt
Classifier: License :: OSI Approved :: BSD License
Classifier: Programming Language :: Python
Classifier: Programming Language :: Python :: 3
Classifier: Programming Language :: Python :: 3.8
Classifier: Programming Language :: Python :: 3.9
Classifier: Programming Language :: Python :: 3.10
Classifier: Programming Language :: Python :: 3.11
Classifier: Programming Language :: Python :: 3.12
Requires-Python: >=3.8
Requires-Dist: jupyter-server<3,>=2.0.1
